genomkit/__init__.py
genomkit/alignments/__init__.py
genomkit/alignments/galignments.py
genomkit/annotation/__init__.py
genomkit/annotation/gannotation.py
genomkit/coverages/__init__.py
genomkit/coverages/gcoverages.py
genomkit/coverages/gcoverages_set.py
genomkit/data/chrom_size/chrom.sizes.hg19
genomkit/data/chrom_size/chrom.sizes.hg38
genomkit/data/chrom_size/chrom.sizes.mm10
genomkit/data/chrom_size/chrom.sizes.mm39
genomkit/data/chrom_size/chrom.sizes.mm9
genomkit/data/chrom_size/chrom.sizes.tair10
genomkit/data/chrom_size/chrom.sizes.zv10
genomkit/data/chrom_size/chrom.sizes.zv9
genomkit/regions/__init__.py
genomkit/regions/gregion.py
genomkit/regions/gregions.py
genomkit/regions/gregions_intervaltree.py
genomkit/regions/gregions_set.py
genomkit/regions/io.py
genomkit/regions/util.py
genomkit/sequences/__init__.py
genomkit/sequences/gsequence.py
genomkit/sequences/gsequences.py
genomkit/sequences/io.py
genomkit/variants/__init__.py
genomkit/variants/gvariant.py
genomkit/variants/gvariants.py
tests/__init__.py
tests/test_gannotation.py
tests/test_gcoverages.py
tests/test_gregion.py
tests/test_gregions.py
tests/test_gregionstree.py
tests/test_gsequence.py
tests/test_gsequences.py
genomkit-0.2.8.dist-info/LICENSE
genomkit-0.2.8.dist-info/METADATA
genomkit-0.2.8.dist-info/WHEEL
genomkit-0.2.8.dist-info/top_level.txt
genomkit-0.2.8.dist-info/RECORD
