Metadata-Version: 2.1
Name: genomkit
Version: 0.2.8
Summary: genomkit
Home-page: https://github.com/chaochungkuo/genomkit
Author: Chao-Chung Kuo
Author-email: chao-chung.kuo@rwth-aachen.de
License: UNKNOWN
Platform: UNKNOWN
Classifier: Programming Language :: Python :: 3
Classifier: License :: OSI Approved :: MIT License
Classifier: Operating System :: OS Independent
License-File: LICENSE
Requires-Dist: intervaltree
Requires-Dist: numpy
Requires-Dist: pandas
Requires-Dist: pyBigWig (==0.3.22)
Requires-Dist: pysam (==0.22.0)
Requires-Dist: scipy
Requires-Dist: tqdm
